alibabacloud_dianjin20240628/__init__.py
alibabacloud_dianjin20240628/client.py
alibabacloud_dianjin20240628/models/__init__.py
alibabacloud_dianjin20240628/models/_create_annual_doc_summary_task_request.py
alibabacloud_dianjin20240628/models/_create_annual_doc_summary_task_response.py
alibabacloud_dianjin20240628/models/_create_annual_doc_summary_task_response_body.py
alibabacloud_dianjin20240628/models/_create_dialog_analysis_task_request.py
alibabacloud_dianjin20240628/models/_create_dialog_analysis_task_response.py
alibabacloud_dianjin20240628/models/_create_dialog_analysis_task_response_body.py
alibabacloud_dianjin20240628/models/_create_dialog_request.py
alibabacloud_dianjin20240628/models/_create_dialog_response.py
alibabacloud_dianjin20240628/models/_create_dialog_response_body.py
alibabacloud_dianjin20240628/models/_create_docs_summary_task_request.py
alibabacloud_dianjin20240628/models/_create_docs_summary_task_response.py
alibabacloud_dianjin20240628/models/_create_docs_summary_task_response_body.py
alibabacloud_dianjin20240628/models/_create_fin_report_summary_task_request.py
alibabacloud_dianjin20240628/models/_create_fin_report_summary_task_response.py
alibabacloud_dianjin20240628/models/_create_fin_report_summary_task_response_body.py
alibabacloud_dianjin20240628/models/_create_image_detection_task_headers.py
alibabacloud_dianjin20240628/models/_create_image_detection_task_request.py
alibabacloud_dianjin20240628/models/_create_image_detection_task_response.py
alibabacloud_dianjin20240628/models/_create_image_detection_task_response_body.py
alibabacloud_dianjin20240628/models/_create_library_request.py
alibabacloud_dianjin20240628/models/_create_library_response.py
alibabacloud_dianjin20240628/models/_create_library_response_body.py
alibabacloud_dianjin20240628/models/_create_pdf_translate_task_request.py
alibabacloud_dianjin20240628/models/_create_pdf_translate_task_response.py
alibabacloud_dianjin20240628-1.19.2.dist-info/LICENSE
alibabacloud_dianjin20240628-1.19.2.dist-info/METADATA
alibabacloud_dianjin20240628-1.19.2.dist-info/WHEEL
alibabacloud_dianjin20240628-1.19.2.dist-info/top_level.txt
alibabacloud_dianjin20240628-1.19.2.dist-info/RECORD
